db_report/__init__.py
db_report/__main__.py
db_report/config/__init__.py
db_report/data/config.json
db_report/data/config_debug.json
db_report/data/ide.tar.gz
db_report/data/locale/en/LC_MESSAGES/db_report.mo
db_report/data/locale/en/LC_MESSAGES/db_report.pot
db_report/data/locale/ru/LC_MESSAGES/db_report.mo
db_report/data/locale/ru/LC_MESSAGES/db_report.pot
db_report/data/reports/test_csv.json
db_report/data/reports/test_json.json
db_report/data/reports/test_postgresql_csv.json
db_report/data/reports/test_psycopg2_csv.json
db_report/data/reports/test_sqlite3_csv.json
db_report/data/reports/test_sqlite3_xls.json
db_report/data/reports/test_sqlite3_xls.xml
db_report/data/reports/test_tab.json
db_report/data/reports/test_xls.json
db_report/data/reports/test_xls.xml
db_report/data/test/chinook.sqlite
db_report/data/test/get_data_csv.py
db_report/data/test/get_data_json.py
db_report/data/test/get_data_tab.py
db_report/data/test/get_data_xls.py
db_report/formats/csv.py
db_report/formats/json.py
db_report/formats/tab.py
db_report/formats/xls.py
db_report/test/test.sh
db_report/test/test_clean.sh
db_report/test/test_debug.sh
db_report/utils/callback.py
db_report/utils/helpers.py
db_report-0.0.12.dist-info/LICENSE
db_report-0.0.12.dist-info/METADATA
db_report-0.0.12.dist-info/WHEEL
db_report-0.0.12.dist-info/entry_points.txt
db_report-0.0.12.dist-info/top_level.txt
db_report-0.0.12.dist-info/RECORD
