Metadata-Version: 2.1
Name: db_report
Version: 0.0.12
Summary: Database report generation
Home-page: https://github.com/oleglpts/reporter
Author: Oleg Lupats
Author-email: oleglupats@gmail.com
License: MIT
Platform: any
Classifier: Operating System :: POSIX
Classifier: Programming Language :: Python :: 3
Classifier: Programming Language :: Python :: 3.5
Requires-Python: >=3
License-File: LICENSE
Requires-Dist: xls-report >=0.0.5
Requires-Dist: bottle >=0.12.17
Requires-Dist: pyodbc >=4.0.26
Requires-Dist: pycurl >=7.43.0.3
Requires-Dist: psycopg2-binary >=2.9.1
